examples
geobricks_mapclassify
geobricks_mapclassify_test
