Metadata-Version: 1.0
Name: GeobricksMapClassify
Version: 0.0.8
Summary: Geobricks .
Home-page: http://pypi.python.org/pypi/GeobricksMapClassify/
Author: Simone Murzilli; Guido Barbaglia
Author-email: geobrickspy@gmail.com
License: LICENSE.txt
Keywords: geobricks,geoserver,sld,mapclassify,choropleth map
Platform: UNKNOWN
